{
    "hasMore": true,
    "totalMatches": 202882,
    "timeSpent": 191,
    "hits": [
        {
            "slug": "https://onlyfans.com/janeil123",
            "profilePic": "https://public.onlyfans.com/files/v/vr/vre/vregisqs6l4w9zfgkpwznujnmodrqzyc1595883095/avatar.jpg",
            "headerPhoto": "https://public.onlyfans.com/files/j/jx/jxj/jxjhdpmlbuavei4o4k88ffcip23e5hzk1595883097/header.jpg",
            "displayName": "Savnanii",
            "info": "Wussap I\u2019m ari",
            "location": "The clouds",
            "website": "",
            "instagramLink": "",
            "twitterLink": "",
            "joinDate": "2020-07-08T00:00:00.000Z",
            "isVerified": true,
            "subscribePrice": 20,
            "subscribersCount": 17,
            "likes": 9,
            "photosCount": 3,
            "videosCount": 3,
            "objectID": "nOyJ3IAB4ze3siaQKQnv"
        },
        {
            "slug": "https://onlyfans.com/jadastl",
            "profilePic": "https://public.onlyfans.com/files/7/78/78h/78h0mtqwrxaxz0pp0nwmqyhbppyby91m1594229815/avatar.jpg",
            "headerPhoto": "https://public.onlyfans.com/files/t/ts/tsq/tsq3dw9kinomtiubjflu7m3pwrak2s2f1594317534/header.jpg",
            "displayName": "Jada Lauren",
            "info": "Hey thank you for checking out my page\ud83d\ude0a Please send me a message if you have any special requests-or if you just want to talk\ud83d\udc93<br />\n<br />\nDon\u2019t be shy I don\u2019t bite\ud83d\ude09",
            "location": "",
            "website": "",
            "instagramLink": "",
            "twitterLink": "",
            "joinDate": "2020-03-31T00:00:00.000Z",
            "isVerified": false,
            "subscribePrice": 50,
            "subscribersCount": 0,
            "likes": 9,
            "photosCount": 13,
            "videosCount": 0,
            "objectID": "bnuJ3IABk-BqQhcCKa7t"
        },
        {
            "slug": "https://onlyfans.com/jessiskywalker",
            "profilePic": "https://public.onlyfans.com/files/5/50/507/507slejsbwpoxgk3vd6fb9sqpko7om2f1603141153/avatar.jpg",
            "headerPhoto": "https://public.onlyfans.com/files/u/ut/utg/utggrkdjwesnnqwarkrncfocznnajrf31603208810/header.jpg",
            "displayName": "Jessica Howard",
            "info": "Just here to post beautiful pictures I took, and some fun extras too. <span class=\"emoji-outer emoji-sizer\"><span class=\"emoji-inner emoji1f609\"></span></span>",
            "location": "Indiana",
            "website": "",
            "instagramLink": "",
            "twitterLink": "",
            "joinDate": "2020-10-03T00:00:00.000Z",
            "isVerified": false,
            "subscribePrice": 4.99,
            "subscribersCount": 805,
            "likes": 9,
            "photosCount": 15,
            "videosCount": 0,
            "objectID": "neyJ3IAB4ze3siaQKQnx"
        },
        {
            "slug": "https://onlyfans.com/itsyourfavorite",
            "profilePic": "https://public.onlyfans.com/files/y/yq/yqd/yqdwm2o7jwm7bwlzbk8acvbpmwxpoxax1598997822/avatar.jpg",
            "headerPhoto": "https://public.onlyfans.com/files/8/8d/8dd/8ddwvfya6j89uvjqobitu0cuvsey6f331599001204/header.jpg",
            "displayName": "Sinay\ud83d\udc8b",
            "info": "\ud83c\udf3925|  some Uncensored Posts not on other Socials\u2728",
            "location": "",
            "website": "",
            "instagramLink": "",
            "twitterLink": "",
            "joinDate": "2020-09-01T00:00:00.000Z",
            "isVerified": false,
            "subscribePrice": 0,
            "subscribersCount": 1,
            "likes": 9,
            "photosCount": 8,
            "videosCount": 2,
            "objectID": "cXuJ3IABk-BqQhcCKa72"
        },
        {
            "slug": "https://onlyfans.com/juicyprincess",
            "profilePic": "https://public.onlyfans.com/files/d/dz/dz3/dz3obiojbliuxmftgc7slwzv46fnb9pm1569665423/avatar.jpg",
            "headerPhoto": "https://public.onlyfans.com/files/6/6x/6xl/6xlcqcll8vgh7t2icmb5vcw1sqmj5dfi1569609176/header.jpg",
            "displayName": "juicyprincess",
            "info": "18 year old juicy princess with exclusive pictures and vids \ud83d\ude18 message me for requests \ud83c\udf52",
            "location": "",
            "website": "",
            "instagramLink": "",
            "twitterLink": "",
            "joinDate": "2019-09-26T00:00:00.000Z",
            "isVerified": false,
            "subscribePrice": 15,
            "subscribersCount": 19,
            "likes": 9,
            "photosCount": 10,
            "videosCount": 5,
            "objectID": "dXuJ3IABk-BqQhcCKq4Y"
        },
        {
            "slug": "https://onlyfans.com/kittyjade",
            "profilePic": "https://public.onlyfans.com/files/g/gk/gk5/gk5qew8jwp8fmmsigkbh2yqtfjgp1cy81594005606/avatar.jpg",
            "headerPhoto": "https://public.onlyfans.com/files/a/af/aft/aftilmz8fkcn0oyprp98w8m4yprk2j961594005607/header.jpg",
            "displayName": "Kitty\ud83d\ude18\ud83d\ude08",
            "info": "Just living life, show me some love \u2764\ufe0f\ud83e\udd70\ud83d\ude18 Subscribe to satisfy your wildest dreams \ud83d\udca6\ud83d\ude08<br />\nSend me tips for more rated photos\ud83d\ude08",
            "location": "",
            "website": "",
            "instagramLink": "",
            "twitterLink": "",
            "joinDate": "2020-07-05T00:00:00.000Z",
            "isVerified": false,
            "subscribePrice": 10,
            "subscribersCount": 0,
            "likes": 9,
            "photosCount": 13,
            "videosCount": 0,
            "objectID": "enuJ3IABk-BqQhcCKq4r"
        },
        {
            "slug": "https://onlyfans.com/kxysb",
            "profilePic": "https://public.onlyfans.com/files/h/hs/hss/hsshlelcyr3fvum1qfoslhq8evts3eo41587487630/avatar.jpg",
            "headerPhoto": "https://public.onlyfans.com/files/m/mz/mzd/mzdikb2tgivvcbuzcnsfjurbvubes4uo1586606761/header.jpg",
            "displayName": "Kevin P.",
            "info": "Broke with expensive taste.<br />\n<br />\nIn here, I\u2019ll release some for-your-eyes-only content. I\u2019ve got a bunch of them so might as well make some dough!<br />\n<br />\nGo and support my fancy lifestyle while enjoying my nudes!<br />\n<br />\nThanks babes! ;)",
            "location": "Paris",
            "website": "https://instagram.com/kxysb",
            "instagramLink": "https://instagram.com/kxysb",
            "twitterLink": "https://instagram.com/kxysb",
            "joinDate": "2020-04-11T00:00:00.000Z",
            "isVerified": true,
            "subscribePrice": 8,
            "subscribersCount": 1,
            "likes": 9,
            "photosCount": 5,
            "videosCount": 1,
            "objectID": "fXuJ3IABk-BqQhcCKq42"
        },
        {
            "slug": "https://onlyfans.com/latinanatural",
            "profilePic": "https://public.onlyfans.com/files/a/ap/apm/apmgymuxjoplgikqrrhh0hwbhrh3n27j1599432412/avatar.jpg",
            "headerPhoto": "https://public.onlyfans.com/files/d/da/dad/dadkmmnjyeachoh5fuoeywrybwjyukri1599432772/header.jpg",
            "displayName": "latinanatural",
            "info": "Chat with me, daily messages, weekly posts, solo content only, clothed/no nudes, no face",
            "location": "NYC",
            "website": "",
            "instagramLink": "",
            "twitterLink": "",
            "joinDate": "2020-09-05T00:00:00.000Z",
            "isVerified": false,
            "subscribePrice": 6,
            "subscribersCount": 4,
            "likes": 9,
            "photosCount": 9,
            "videosCount": 0,
            "objectID": "fHuJ3IABk-BqQhcCKq40"
        },
        {
            "slug": "https://onlyfans.com/luvlondy",
            "profilePic": "https://public.onlyfans.com/files/j/ji/jil/jilupn9jzq5pvcrxaicjntnyblhc74yd1603420769/avatar.jpg",
            "headerPhoto": "https://public.onlyfans.com/files/f/fe/feu/feubkumt4ty3alcklhhn73vwxqrbudyg1603443120/header.jpg",
            "displayName": "Luvlondy \ud83e\udd0d",
            "info": "Ultimate tease/ fantasy <br />\n18 and older content <br />\nExclusive content <br />\nCustom requests ($$) <br />\nDaily chats with you <br />\nConsistent posts <br />\nRatings <span class=\"emoji-outer emoji-sizer\"><span class=\"emoji-inner emoji2b50\"></span></span><span class=\"emoji-outer emoji-sizer\"><span class=\"emoji-inner emoji2b50\"></span></span><span class=\"emoji-outer emoji-sizer\"><span class=\"emoji-inner emoji2b50\"></span></span><span class=\"emoji-outer emoji-sizer\"><span class=\"emoji-inner emoji2b50\"></span></span><span class=\"emoji-outer emoji-sizer\"><span class=\"emoji-inner emoji2b50\"></span></span><br />\nSexy fun &amp; kinky photographs <br />\nLET\u2019S HAVE SOME FUN \ud83e\udd0d<br />\n<br />\nTip Menu:<br />\n$45/day - Boyfriend Experience <br />\n$20 - d i c k rating <br />\n$15 - p u s s y pic <br />\n$50 - custom video",
            "location": "Houston",
            "website": "https://www.instagram.com/luvlondy/",
            "instagramLink": "https://www.instagram.com/luvlondy/",
            "twitterLink": "https://www.instagram.com/luvlondy/",
            "joinDate": "2020-01-18T00:00:00.000Z",
            "isVerified": true,
            "subscribePrice": 6,
            "subscribersCount": 0,
            "likes": 9,
            "photosCount": 9,
            "videosCount": 1,
            "objectID": "g3uJ3IABk-BqQhcCKq5V"
        },
        {
            "slug": "https://onlyfans.com/madison-bird",
            "profilePic": "https://public.onlyfans.com/files/i/ig/igd/igd0nun2w953ydh14ikwffyqmlury0hm1599534125/avatar.jpg",
            "headerPhoto": "https://public.onlyfans.com/files/p/px/pxs/pxsju931akchrirjeygqjjpqbb8nlfap1599534125/header.jpg",
            "displayName": "Madison Bird",
            "info": "Thick ass, thin wallet",
            "location": "Georgia",
            "website": "",
            "instagramLink": "",
            "twitterLink": "",
            "joinDate": "2020-09-01T00:00:00.000Z",
            "isVerified": true,
            "subscribePrice": 14.99,
            "subscribersCount": 1957,
            "likes": 9,
            "photosCount": 9,
            "videosCount": 0,
            "objectID": "hXuJ3IABk-BqQhcCKq5j"
        },
        {
            "slug": "https://onlyfans.com/mayafox2002",
            "profilePic": "https://public.onlyfans.com/files/k/k3/k3x/k3xppq46cbcd6w1loqt7phnkwbeebbiw1596757452/avatar.jpg",
            "headerPhoto": "https://public.onlyfans.com/files/s/sn/snu/snujybkvhluckqx8dwx4gfdmmicx1njq1596783623/header.jpg",
            "displayName": "Maya Fox",
            "info": "Hey babes, I just turned 18 on August 3rd. I'm a new student in the Bay Area. I'm currently on my own and tight on money so I thought maybe this would help me with my living situation/school. YES, I take requests, tips, and private photos.",
            "location": "San Francisco",
            "website": "",
            "instagramLink": "",
            "twitterLink": "",
            "joinDate": "2020-08-05T00:00:00.000Z",
            "isVerified": false,
            "subscribePrice": 26.99,
            "subscribersCount": 33,
            "likes": 9,
            "photosCount": 9,
            "videosCount": 0,
            "objectID": "iXuJ3IABk-BqQhcCKq5q"
        },
        {
            "slug": "https://onlyfans.com/lynielovegood",
            "profilePic": "https://public.onlyfans.com/files/3/3h/3hs/3hsrdh7wb3xxbpwqvnt1j67hb9i0km2p1601842731/avatar.jpg",
            "headerPhoto": "https://public.onlyfans.com/files/e/et/ety/etyjsfvna1vkzcptyqfflldkmyfaioad1601495297/header.jpg",
            "displayName": "Lyndsey \ud83d\udda4",
            "info": "BBW Content// Just here for fun :)<br />\nTell me what you want to see &lt;3",
            "location": "California",
            "website": "",
            "instagramLink": "",
            "twitterLink": "",
            "joinDate": "2020-09-28T00:00:00.000Z",
            "isVerified": true,
            "subscribePrice": 10,
            "subscribersCount": 7,
            "likes": 9,
            "photosCount": 1,
            "videosCount": 5,
            "objectID": "h3uJ3IABk-BqQhcCKq5m"
        },
        {
            "slug": "https://onlyfans.com/missaries1",
            "profilePic": "https://public.onlyfans.com/files/v/vf/vfg/vfgzwvkzgp7cwjghkqgohzrqpgn06cyb1580307445/avatar.jpg",
            "headerPhoto": "https://public.onlyfans.com/files/v/vm/vmx/vmxcmzll2kchfcwlbkq5oojlazw9fwac1580048973/header.jpg",
            "displayName": "MissAries",
            "info": "Hello loves. <br />\n5'1 chubby babe for you \u2665 <br />\nMake my day and tip me, love \u2665",
            "location": "",
            "website": "",
            "instagramLink": "",
            "twitterLink": "",
            "joinDate": "2020-01-26T00:00:00.000Z",
            "isVerified": false,
            "subscribePrice": 5,
            "subscribersCount": 271,
            "likes": 9,
            "photosCount": 14,
            "videosCount": 2,
            "objectID": "j3uJ3IABk-BqQhcCKq6Q"
        },
        {
            "slug": "https://onlyfans.com/mrpeaches",
            "profilePic": "https://public.onlyfans.com/files/4/4c/4c7/4c7xv49ifh9nrbp67aicgrkrqga0gdwj1594229703/avatar.jpg",
            "headerPhoto": "https://public.onlyfans.com/files/i/iu/iu6/iu63dm6arhggt7m2lo41pjxywlqvu9yv1594229704/header.jpg",
            "displayName": "Gregory Peaches",
            "info": "Just your average hung stud with a taste for the fancy life. Let me know what you want to see.",
            "location": "Mt.Zion",
            "website": "",
            "instagramLink": "",
            "twitterLink": "",
            "joinDate": "2020-05-24T00:00:00.000Z",
            "isVerified": true,
            "subscribePrice": 0,
            "subscribersCount": 1709,
            "likes": 9,
            "photosCount": 3,
            "videosCount": 0,
            "objectID": "r-yJ3IAB4ze3siaQKgme"
        },
        {
            "slug": "https://onlyfans.com/noamoon",
            "profilePic": "https://public.onlyfans.com/files/7/7t/7t6/7t6j3jk0wejgsxubra9k95uwdadfovcl1596201188/avatar.jpg",
            "headerPhoto": "https://public.onlyfans.com/files/l/lo/lok/lokf1oi5lfbmo6q5edcaqe0evzbmi0uv1596813613/header.jpg",
            "displayName": "Noa.Moon",
            "info": "Angelic freckle face with a little bikini bod &lt;3<br />\nluxurious lingerie, elegant seductive content and/or personal request<br />\nxx",
            "location": "",
            "website": "",
            "instagramLink": "",
            "twitterLink": "",
            "joinDate": "2020-07-31T00:00:00.000Z",
            "isVerified": false,
            "subscribePrice": 13.99,
            "subscribersCount": 15,
            "likes": 9,
            "photosCount": 14,
            "videosCount": 0,
            "objectID": "s-yJ3IAB4ze3siaQKgmo"
        },
        {
            "slug": "https://onlyfans.com/nofazeguy",
            "profilePic": "https://public.onlyfans.com/files/c/cs/csl/cslo2azpfkzxvbxvigwlnu8fyesbopaz1603058973/avatar.jpg",
            "headerPhoto": "https://public.onlyfans.com/files/6/6w/6wj/6wjlxjlc2t3vepbm0tsuwbdotdb70xpu1603058974/header.jpg",
            "displayName": "No Faze Guy \ud83d\udd25\ud83d\udd1e",
            "info": "<span class=\"emoji-outer emoji-sizer\"><span class=\"emoji-inner emoji1f514\"></span></span> ALL YOU NEED TO KNOW <span class=\"emoji-outer emoji-sizer\"><span class=\"emoji-inner emoji1f514\"></span></span><br />\n<br />\nHey, I'm a straight guy how posts pics and videos of his body (underwear etc.).<br />\n<br />\nPlease DON'T ask for face pics, I absolutely cannot because of my  job! Sorry.<br />\n<br />\n\u2022 AT THE MOMENT FREE SUBSCRIBING. LATER IT WILL COST $14.99 USD.<br />\n<br />\n\u2022 REMAIN ANONYMOUS (if you prefer)<br />\n<br />\n\u2022 THIS IS FOR 18+ ONLY<br />\n<br />\n\u2022 MALE + FEMALE CONTENT<br />\n<br />\n\u2022 I ONLY TAKE AMATEUR PHOTOS AS YOU CAN SEE BELOW. IN MY OPINION THIS IS MORE REAL.<br />\n<br />\n\u2022 I HAVE ALSO BLOCKED MY PAGE FROM BEING VIEWED IN SOME COUNTRIES.",
            "location": "In your Phantasie",
            "website": "",
            "instagramLink": "",
            "twitterLink": "",
            "joinDate": "2020-10-16T00:00:00.000Z",
            "isVerified": false,
            "subscribePrice": 0,
            "subscribersCount": 5,
            "likes": 9,
            "photosCount": 9,
            "videosCount": 2,
            "objectID": "lXuJ3IABk-BqQhcCKq6o"
        },
        {
            "slug": "https://onlyfans.com/operaphantom",
            "profilePic": "https://public.onlyfans.com/files/n/ny/nyn/nynpjvq2phkknm8kjewyitc1fha7bkuc1584907349/avatar.jpg",
            "headerPhoto": "https://public.onlyfans.com/files/l/l7/l7w/l7wwvravynidlkc740uiozgtorhfnm8r1583826652/header.jpg",
            "displayName": "Phantom",
            "info": "Follow for male solo content \ud83d\ude0e\ud83e\udd2a",
            "location": "Wakanda",
            "website": "",
            "instagramLink": "",
            "twitterLink": "",
            "joinDate": "2019-02-21T00:00:00.000Z",
            "isVerified": false,
            "subscribePrice": 7.99,
            "subscribersCount": 4,
            "likes": 9,
            "photosCount": 6,
            "videosCount": 1,
            "objectID": "tuyJ3IAB4ze3siaQKgmv"
        },
        {
            "slug": "https://onlyfans.com/ravenwolfe4",
            "profilePic": "https://public.onlyfans.com/files/b/bx/bx3/bx3fielshrfsobexgmv1mxdxphm6wlov1601037581/avatar.jpg",
            "headerPhoto": "https://public.onlyfans.com/files/t/tt/ttv/ttvxy6ww3hcejerhjtvkfsgqoizlymju1601037584/header.jpg",
            "displayName": "Raven Wolfe",
            "info": "Come along for fun themed photo shoots! \ud83c\udf3bMy opening photoshoot is the theme \u201cLate Night Snack\u201d. I will be doing more elaborate pinup style shoots! My Amazon wishlist will be filled with different props for photo sessions so you get to choose what I do next by purchasing!",
            "location": "World",
            "website": "",
            "instagramLink": "",
            "twitterLink": "",
            "joinDate": "2020-09-25T00:00:00.000Z",
            "isVerified": true,
            "subscribePrice": 5,
            "subscribersCount": 105,
            "likes": 9,
            "photosCount": 4,
            "videosCount": 0,
            "objectID": "veyJ3IAB4ze3siaQKgnM"
        },
        {
            "slug": "https://onlyfans.com/sweetdea",
            "profilePic": "https://public.onlyfans.com/files/s/s5/s5w/s5wb3snr4irhlnveivomf91esfj5cxco1599225222/avatar.jpg",
            "headerPhoto": "https://public.onlyfans.com/files/s/s5/s57/s5771hxg4ihpsam4zyxic6wv8lzsqvn71599225250/header.jpg",
            "displayName": "Dea",
            "info": "26 \u2022 pierced tits &amp; daddy issues.",
            "location": "",
            "website": "",
            "instagramLink": "",
            "twitterLink": "",
            "joinDate": "2020-09-04T00:00:00.000Z",
            "isVerified": false,
            "subscribePrice": 4.99,
            "subscribersCount": 28,
            "likes": 9,
            "photosCount": 1,
            "videosCount": 0,
            "objectID": "yOyJ3IAB4ze3siaQKgn-"
        },
        {
            "slug": "https://onlyfans.com/spankedglassass-premium",
            "profilePic": "https://public.onlyfans.com/files/z/zf/zfu/zfuvmh7k5shvmz3lrlfdeiznunywnlf51597694365/avatar.jpg",
            "headerPhoto": "https://public.onlyfans.com/files/m/m3/m3s/m3sjzjqymst04heqm5jknnu7yavd378z1597694624/header.jpg",
            "displayName": "spankedglassass-premium",
            "info": "Top quality premium content that will make your mouth water",
            "location": "Florida",
            "website": "",
            "instagramLink": "",
            "twitterLink": "",
            "joinDate": "2020-08-17T00:00:00.000Z",
            "isVerified": false,
            "subscribePrice": 9.99,
            "subscribersCount": 3762,
            "likes": 9,
            "photosCount": 5,
            "videosCount": 4,
            "objectID": "rHuJ3IABk-BqQhcCKq72"
        }
    ]
}